tkinter_form/__init__.py
tkinter_form/field_form.py
tkinter_form/tkinter_form.py
tkinter_form-0.2.dist-info/METADATA
tkinter_form-0.2.dist-info/WHEEL
tkinter_form-0.2.dist-info/licenses/LICENSE
tkinter_form-0.2.dist-info/RECORD
