Metadata-Version: 2.3
Name: tkinter-form
Version: 0.2
Summary: form for tkinter
Project-URL: Homepage, https://github.com/JohanEstebanCuervo/tkinter_form
Project-URL: Bug Tracker, https://github.com/JohanEstebanCuervo/tkinter_form/issues
Author-email: JohanEstebanCuervo <jecuervoch@unal.edu.co>
License: Copyright (c) 2012-2023 Scott Chacon and others
License-File: LICENSE
Classifier: Development Status :: 1 - Planning
Classifier: Intended Audience :: Developers
Classifier: Operating System :: MacOS :: MacOS X
Classifier: Operating System :: Microsoft :: Windows
Classifier: Operating System :: Unix
Classifier: Programming Language :: Python :: 3
Requires-Python: >=3.6
